fuckor/__init__.py
fuckor/py.py
Kirs_fucker-2.0.dist-info/LICENSE
Kirs_fucker-2.0.dist-info/METADATA
Kirs_fucker-2.0.dist-info/WHEEL
Kirs_fucker-2.0.dist-info/top_level.txt
Kirs_fucker-2.0.dist-info/RECORD
