Metadata-Version: 2.1
Name: Kirs-fucker
Version: 2.0
Summary: 一个非常niuB的包
Home-page: UNKNOWN
Author: WangYaNan
Author-email: wangyanan0605@qq.com
License: UNKNOWN
Platform: UNKNOWN
Classifier: Programming Language :: Python :: 3
Classifier: License :: OSI Approved :: MIT License
Classifier: Operating System :: OS Independent
Requires-Python: >=3
Requires-Dist: pillow
